dodam_api/__init__.py
dodam_api/api.py
dodam_api/apis/__init__.py
dodam_api/apis/auth.py
dodam_api/apis/banner.py
dodam_api/apis/bus.py
dodam_api/apis/member.py
dodam_api/apis/nightstudy.py
dodam_api/apis/point.py
dodam_api/client.py
dodam_api/error.py
dodam_api/utils.py
dodam_api-1.0.5.dist-info/LICENSE.txt
dodam_api-1.0.5.dist-info/METADATA
dodam_api-1.0.5.dist-info/WHEEL
dodam_api-1.0.5.dist-info/RECORD
